czip/__init__.py
czip/allc.py
czip/cz.py
ChunkZIP-0.4.1.dist-info/LICENSE
ChunkZIP-0.4.1.dist-info/METADATA
ChunkZIP-0.4.1.dist-info/WHEEL
ChunkZIP-0.4.1.dist-info/top_level.txt
ChunkZIP-0.4.1.dist-info/RECORD
