Metadata-Version: 2.1
Name: ChunkZIP
Version: 0.4.1
Summary: ChunkZIP: Chunk based ZIP
Home-page: https://github.com/DingWB/czip
Author: Wubin Ding
Author-email: Wubin Ding <ding.wu.bin.gm@gmail.com>
License: GNU GENERAL PUBLIC LICENSE
Project-URL: Homepage, https://github.com/DingWB/czip
Project-URL: repository, https://github.com/DingWB/czip
Project-URL: Bug Tracker, https://github.com/DingWB/czip/issues
Project-URL: documentation, https://dingwb.github.io/czip
Keywords: ChunkZIP,czip
Classifier: Programming Language :: Python :: 3
Classifier: License :: OSI Approved :: GNU General Public License v3 or later (GPLv3+)
Classifier: Operating System :: OS Independent
Requires-Python: >=3.0
License-File: LICENSE
